{
  "name": "City Map 47",
  "type": "map",
  "mapType": "city",
  "gridSize": null,
  "scale": "1:10000",
  "tags": [
    "map",
    "city",
    "cartography",
    "generated"
  ],
  "locations": [
    {
      "name": "Location 1",
      "x": 2.3957437960635986,
      "y": 84.90656125669425,
      "type": "city"
    },
    {
      "name": "Location 2",
      "x": 84.85825268828808,
      "y": 61.73799536871043,
      "type": "town"
    },
    {
      "name": "Location 3",
      "x": 61.16411453470162,
      "y": 75.22770839459945,
      "type": "dungeon"
    },
    {
      "name": "Location 4",
      "x": 43.929063720467,
      "y": 41.67944631694612,
      "type": "town"
    },
    {
      "name": "Location 5",
      "x": 75.9226355133689,
      "y": 93.87371373121654,
      "type": "dungeon"
    }
  ],
  "created": "2025-08-16T16:58:14.571Z"
}