{
  "name": "City Map 152",
  "type": "map",
  "mapType": "city",
  "gridSize": null,
  "scale": "1:10000",
  "tags": [
    "map",
    "city",
    "cartography",
    "generated"
  ],
  "locations": [
    {
      "name": "Location 1",
      "x": 58.28699219711052,
      "y": 92.33993899712452,
      "type": "landmark"
    },
    {
      "name": "Location 2",
      "x": 25.531804567580863,
      "y": 18.533179312835635,
      "type": "city"
    },
    {
      "name": "Location 3",
      "x": 30.717042262542627,
      "y": 1.9315172097341238,
      "type": "landmark"
    },
    {
      "name": "Location 4",
      "x": 48.591622778921874,
      "y": 7.204447313015594,
      "type": "city"
    },
    {
      "name": "Location 5",
      "x": 68.2595329092144,
      "y": 73.00013359594223,
      "type": "landmark"
    }
  ],
  "created": "2025-08-16T16:58:14.625Z"
}