{
  "name": "City Map 262",
  "type": "map",
  "mapType": "city",
  "gridSize": null,
  "scale": "1:10000",
  "tags": [
    "map",
    "city",
    "cartography",
    "generated"
  ],
  "locations": [
    {
      "name": "Location 1",
      "x": 15.917707713832108,
      "y": 12.72264560152696,
      "type": "town"
    },
    {
      "name": "Location 2",
      "x": 31.727620836275094,
      "y": 29.551074953000743,
      "type": "landmark"
    },
    {
      "name": "Location 3",
      "x": 1.5302415365750388,
      "y": 17.89376217306057,
      "type": "landmark"
    },
    {
      "name": "Location 4",
      "x": 30.17096377176054,
      "y": 39.91586764184626,
      "type": "dungeon"
    },
    {
      "name": "Location 5",
      "x": 48.894767865685594,
      "y": 12.753989462657522,
      "type": "city"
    }
  ],
  "created": "2025-08-16T16:58:14.676Z"
}